meu_pacote/__init__.py
meu_pacote/modulo.py
my_first_library_gugalm_2025-0.0.1.dist-info/licenses/LICENSE
my_first_library_gugalm_2025-0.0.1.dist-info/METADATA
my_first_library_gugalm_2025-0.0.1.dist-info/WHEEL
my_first_library_gugalm_2025-0.0.1.dist-info/top_level.txt
my_first_library_gugalm_2025-0.0.1.dist-info/RECORD
