Metadata-Version: 2.4
Name: my_first_library_gugalm_2025
Version: 0.0.1
Summary: Uma breve descricao do projeto.
Author-email: Seu Nome <seu@email.com>
Project-URL: Homepage, https://github.com/seu_usuario/my_first_library
Project-URL: Issues, https://github.com/seu_usuario/my_first_library/issues
Classifier: Programming Language :: Python :: 3
Classifier: License :: OSI Approved :: MIT License
Classifier: Operating System :: OS Independent
Requires-Python: >=3.8
License-File: LICENSE
Dynamic: license-file
